dpsa4fl_bindings-0.1.69.dist-info/METADATA
dpsa4fl_bindings-0.1.69.dist-info/WHEEL
dpsa4fl_bindings/__init__.py
dpsa4fl_bindings/__init__.pyi
dpsa4fl_bindings/py.typed
dpsa4fl_bindings/dpsa4fl_bindings.cpython-39-x86_64-linux-gnu.so
dpsa4fl_bindings-0.1.69.dist-info/RECORD
