Metadata-Version: 2.1
Name: dpsa4fl-bindings
Version: 0.1.69
Classifier: Programming Language :: Rust
Classifier: Programming Language :: Python :: Implementation :: CPython
Classifier: Programming Language :: Python :: Implementation :: PyPy
Requires-Python: >=3.7
